errno.py
setup.py
micropython_errno.egg-info/PKG-INFO
micropython_errno.egg-info/SOURCES.txt
micropython_errno.egg-info/dependency_links.txt
micropython_errno.egg-info/top_level.txt