Metadata-Version: 1.0
Name: micropython-errno
Version: 0.1.2
Summary: errno module for MicroPython
Home-page: https://github.com/micropython/micropython/issues/405
Author: MicroPython Developers
Author-email: micro-python@googlegroups.com
License: MIT
Platform: UNKNOWN
